Metadata-Version: 2.1
Name: django-split-listview
Version: 2020.7.1
Summary: split Django ListView queryset
Home-page: https://github.com/andrewp-as-is/django-split-listview.py
License: Unlicense
Keywords: django listview
Platform: UNKNOWN
Classifier: Framework :: Django
Classifier: License :: Public Domain
Classifier: Operating System :: OS Independent
Classifier: Programming Language :: Python :: 3
